suzano_image/__init__.py
suzano_image/processor.py
suzano_image-0.1.dist-info/METADATA
suzano_image-0.1.dist-info/WHEEL
suzano_image-0.1.dist-info/top_level.txt
suzano_image-0.1.dist-info/RECORD
