Metadata-Version: 2.4
Name: suzano_image
Version: 0.1
Summary: Pacote de processamento de imagens do Bootcamp da Suzano
Author: Seu Nome
Requires-Dist: opencv-python
Requires-Dist: numpy
Dynamic: author
Dynamic: description
Dynamic: description-content-type
Dynamic: requires-dist
Dynamic: summary
